<?xml version="1.0" encoding="UTF-8"?>
<xmi:XMI xmi:version="2.0" xmlns:xmi="http://www.omg.org/XMI" xmlns:TalendProperties="http://www.talend.org/properties">
  <TalendProperties:Property xmi:id="_yFwNkKoAEeuk8_jpG_RzxQ" id="_yFZBMKoAEeuk8_jpG_RzxQ" label="HiveCreateTargetTable" version="0.1" item="_yFwNkqoAEeuk8_jpG_RzxQ">
    <author href="../../../talend.project#_sugcEaoAEeuk8_jpG_RzxQ"/>
    <additionalProperties xmi:id="_yFxbsKoAEeuk8_jpG_RzxQ" key="created_product_fullname" value="Talend Open Studio for Data Integration"/>
    <additionalProperties xmi:id="_yFxbsaoAEeuk8_jpG_RzxQ" key="created_product_version" value="7.3.1.20200219_1130"/>
    <additionalProperties xmi:id="_yFxbsqoAEeuk8_jpG_RzxQ" key="created_date" value="2021-04-30T23:09:50.315+0100"/>
    <additionalProperties xmi:id="_yFxbs6oAEeuk8_jpG_RzxQ" key="modified_product_fullname" value="Talend Open Studio for Data Integration"/>
    <additionalProperties xmi:id="_yFxbtKoAEeuk8_jpG_RzxQ" key="modified_product_version" value="7.3.1.20200219_1130"/>
    <additionalProperties xmi:id="_yFxbtaoAEeuk8_jpG_RzxQ" key="modified_date" value="2021-04-30T23:09:50.315+0100"/>
  </TalendProperties:Property>
  <TalendProperties:ItemState xmi:id="_yFwNkaoAEeuk8_jpG_RzxQ" path="Hive/system"/>
  <TalendProperties:SQLPatternItem xmi:id="_yFwNkqoAEeuk8_jpG_RzxQ" property="_yFwNkKoAEeuk8_jpG_RzxQ" state="_yFwNkaoAEeuk8_jpG_RzxQ" system="true" eltName="Hive">
    <content href="HiveCreateTargetTable_0.1.item#/"/>
  </TalendProperties:SQLPatternItem>
</xmi:XMI>
